[
    [
        {
            "episode": 1,
            "rating": 7.8,
            "id": "tt0678109"
        },
        {
            "episode": 2,
            "rating": 7.6,
            "id": "tt0678081"
        },
        {
            "episode": 3,
            "rating": 7.5,
            "id": "tt0678086"
        },
        {
            "episode": 4,
            "rating": 7.7,
            "id": "tt0678075"
        },
        {
            "episode": 5,
            "rating": 7.6,
            "id": "tt0678131"
        },
        {
            "episode": 6,
            "rating": 7.7,
            "id": "tt0678134"
        },
        {
            "episode": 7,
            "rating": 7.5,
            "id": "tt0678057"
        },
        {
            "episode": 8,
            "rating": 8.0,
            "id": "tt0678103"
        },
        {
            "episode": 9,
            "rating": 7.4,
            "id": "tt0678099"
        },
        {
            "episode": 10,
            "rating": 7.5,
            "id": "tt0678128"
        },
        {
            "episode": 11,
            "rating": 7.5,
            "id": "tt0678111"
        },
        {
            "episode": 12,
            "rating": 7.3,
            "id": "tt0678112"
        },
        {
            "episode": 13,
            "rating": 7.4,
            "id": "tt0678064"
        },
        {
            "episode": 14,
            "rating": 8.0,
            "id": "tt0678114"
        },
        {
            "episode": 15,
            "rating": 7.2,
            "id": "tt0678094"
        },
        {
            "episode": 16,
            "rating": 7.7,
            "id": "tt0678136"
        },
        {
            "episode": 17,
            "rating": 7.7,
            "id": "tt0678096"
        },
        {
            "episode": 18,
            "rating": 7.5,
            "id": "tt0678137"
        },
        {
            "episode": 19,
            "rating": 7.5,
            "id": "tt0678093"
        },
        {
            "episode": 20,
            "rating": 7.6,
            "id": "tt0678061"
        },
        {
            "episode": 21,
            "rating": 8.2,
            "id": "tt0678078"
        },
        {
            "episode": 22,
            "rating": 8.3,
            "id": "tt0678079"
        }
    ],
    [
        {
            "episode": 1,
            "rating": 7.6,
            "id": "tt0678062"
        },
        {
            "episode": 2,
            "rating": 7.6,
            "id": "tt0678120"
        },
        {
            "episode": 3,
            "rating": 7.7,
            "id": "tt0678105"
        },
        {
            "episode": 4,
            "rating": 7.5,
            "id": "tt0678082"
        },
        {
            "episode": 5,
            "rating": 8.1,
            "id": "tt0678102"
        },
        {
            "episode": 6,
            "rating": 8.3,
            "id": "tt0678108"
        },
        {
            "episode": 7,
            "rating": 8.0,
            "id": "tt0678070"
        },
        {
            "episode": 8,
            "rating": 8.1,
            "id": "tt0678089"
        },
        {
            "episode": 9,
            "rating": 8.4,
            "id": "tt0678084"
        },
        {
            "episode": 10,
            "rating": 7.9,
            "id": "tt0678092"
        },
        {
            "episode": 11,
            "rating": 7.5,
            "id": "tt0394843"
        },
        {
            "episode": 12,
            "rating": 8.0,
            "id": "tt0678135"
        },
        {
            "episode": 13,
            "rating": 8.0,
            "id": "tt0678056"
        },
        {
            "episode": 14,
            "rating": 8.3,
            "id": "tt0678058"
        },
        {
            "episode": 15,
            "rating": 7.8,
            "id": "tt0678068"
        },
        {
            "episode": 16,
            "rating": 8.1,
            "id": "tt0678121"
        },
        {
            "episode": 17,
            "rating": 8.1,
            "id": "tt0678073"
        },
        {
            "episode": 18,
            "rating": 8.4,
            "id": "tt0678124"
        },
        {
            "episode": 19,
            "rating": 8.8,
            "id": "tt0678115"
        },
        {
            "episode": 20,
            "rating": 8.7,
            "id": "tt0678063"
        },
        {
            "episode": 21,
            "rating": 8.4,
            "id": "tt0678066"
        },
        {
            "episode": 22,
            "rating": 8.7,
            "id": "tt0678067"
        }
    ],
    [
        {
            "episode": 1,
            "rating": 8.3,
            "id": "tt0678074"
        },
        {
            "episode": 2,
            "rating": 8.1,
            "id": "tt0678091"
        },
        {
            "episode": 3,
            "rating": 8.4,
            "id": "tt0678104"
        },
        {
            "episode": 4,
            "rating": 7.8,
            "id": "tt0678122"
        },
        {
            "episode": 5,
            "rating": 8.5,
            "id": "tt0678065"
        },
        {
            "episode": 6,
            "rating": 8.2,
            "id": "tt0678107"
        },
        {
            "episode": 7,
            "rating": 7.9,
            "id": "tt0678090"
        },
        {
            "episode": 8,
            "rating": 8.3,
            "id": "tt0394842"
        },
        {
            "episode": 9,
            "rating": 8.2,
            "id": "tt0678101"
        },
        {
            "episode": 10,
            "rating": 7.7,
            "id": "tt0678100"
        },
        {
            "episode": 11,
            "rating": 8.1,
            "id": "tt0678127"
        },
        {
            "episode": 12,
            "rating": 7.8,
            "id": "tt0678138"
        },
        {
            "episode": 13,
            "rating": 8.1,
            "id": "tt0678110"
        },
        {
            "episode": 14,
            "rating": 8.5,
            "id": "tt0678060"
        },
        {
            "episode": 15,
            "rating": 7.8,
            "id": "tt0678072"
        },
        {
            "episode": 16,
            "rating": 7.9,
            "id": "tt0678106"
        },
        {
            "episode": 17,
            "rating": 8.2,
            "id": "tt0678133"
        },
        {
            "episode": 18,
            "rating": 8.5,
            "id": "tt0678139"
        },
        {
            "episode": 19,
            "rating": 8.3,
            "id": "tt0678080"
        },
        {
            "episode": 20,
            "rating": 8.1,
            "id": "tt0678113"
        },
        {
            "episode": 21,
            "rating": 8.7,
            "id": "tt0678076"
        },
        {
            "episode": 22,
            "rating": 8.9,
            "id": "tt0678077"
        }
    ],
    [
        {
            "episode": 1,
            "rating": 8.4,
            "id": "tt0678132"
        },
        {
            "episode": 2,
            "rating": 8.1,
            "id": "tt0678125"
        },
        {
            "episode": 3,
            "rating": 7.8,
            "id": "tt0678059"
        },
        {
            "episode": 4,
            "rating": 8.2,
            "id": "tt0678116"
        },
        {
            "episode": 5,
            "rating": 8.5,
            "id": "tt0678117"
        },
        {
            "episode": 6,
            "rating": 8.0,
            "id": "tt0678083"
        },
        {
            "episode": 7,
            "rating": 8.1,
            "id": "tt0678140"
        },
        {
            "episode": 8,
            "rating": 8.1,
            "id": "tt0678118"
        },
        {
            "episode": 9,
            "rating": 8.6,
            "id": "tt0678055"
        },
        {
            "episode": 10,
            "rating": 8.3,
            "id": "tt0678123"
        },
        {
            "episode": 11,
            "rating": 7.8,
            "id": "tt0678069"
        },
        {
            "episode": 12,
            "rating": 7.7,
            "id": "tt0678097"
        },
        {
            "episode": 13,
            "rating": 7.6,
            "id": "tt0678087"
        },
        {
            "episode": 14,
            "rating": 8.2,
            "id": "tt0678126"
        },
        {
            "episode": 15,
            "rating": 8.3,
            "id": "tt0678095"
        },
        {
            "episode": 16,
            "rating": 8.0,
            "id": "tt0678119"
        },
        {
            "episode": 17,
            "rating": 7.8,
            "id": "tt0678098"
        },
        {
            "episode": 18,
            "rating": 7.9,
            "id": "tt0678071"
        },
        {
            "episode": 19,
            "rating": 8.8,
            "id": "tt0678129"
        },
        {
            "episode": 20,
            "rating": 8.2,
            "id": "tt0678130"
        }
    ]
]