[
    [
        {
            "episode": 1,
            "rating": 8.2
        },
        {
            "episode": 2,
            "rating": 7.5
        },
        {
            "episode": 3,
            "rating": 8.0
        },
        {
            "episode": 4,
            "rating": 8.4
        },
        {
            "episode": 5,
            "rating": 7.6
        },
        {
            "episode": 6,
            "rating": 9.2
        },
        {
            "episode": 7,
            "rating": 7.9
        },
        {
            "episode": 8,
            "rating": 7.8
        },
        {
            "episode": 9,
            "rating": 7.5
        }
    ]
]