[
    [
        {
            "episode": 1,
            "rating": 8.399999618530273,
            "id": "tt5718950"
        },
        {
            "episode": 2,
            "rating": 8.300000190734863,
            "id": "tt5718954"
        },
        {
            "episode": 3,
            "rating": 8.699999809265137,
            "id": "tt5719564"
        },
        {
            "episode": 4,
            "rating": 8.399999618530273,
            "id": "tt5720470"
        },
        {
            "episode": 5,
            "rating": 9.100000381469727,
            "id": "tt5720472"
        },
        {
            "episode": 6,
            "rating": 8.199999809265137,
            "id": "tt5720476"
        },
        {
            "episode": 7,
            "rating": 8.699999809265137,
            "id": "tt5720478"
        },
        {
            "episode": 8,
            "rating": 9.100000381469727,
            "id": "tt5718952"
        }
    ],
    [
        {
            "episode": 1,
            "rating": 7.800000190734863,
            "id": "tt19354770"
        },
        {
            "episode": 2,
            "rating": 7.5,
            "id": "tt21193100"
        },
        {
            "episode": 3,
            "rating": 7.199999809265137,
            "id": "tt21193102"
        },
        {
            "episode": 4,
            "rating": 7.5,
            "id": "tt21193106"
        },
        {
            "episode": 5,
            "rating": 7.300000190734863,
            "id": "tt21193112"
        },
        {
            "episode": 6,
            "rating": 7.0,
            "id": "tt21193116"
        },
        {
            "episode": 7,
            "rating": 7.599999904632568,
            "id": "tt21193128"
        },
        {
            "episode": 8,
            "rating": 6.699999809265137,
            "id": "tt21193132"
        }
    ]
]