[
    [
        {
            "episode": 1,
            "rating": 7.9
        },
        {
            "episode": 2,
            "rating": 8.7
        },
        {
            "episode": 3,
            "rating": 8.3
        },
        {
            "episode": 4,
            "rating": 8.7
        },
        {
            "episode": 5,
            "rating": 9.0
        },
        {
            "episode": 6,
            "rating": 9.0
        },
        {
            "episode": 7,
            "rating": 7.9
        },
        {
            "episode": 8,
            "rating": 8.7
        },
        {
            "episode": 9,
            "rating": 8.4
        },
        {
            "episode": 10,
            "rating": 9.3
        },
        {
            "episode": 11,
            "rating": 8.4
        }
    ],
    [
        {
            "episode": 1,
            "rating": 8.8
        },
        {
            "episode": 2,
            "rating": 8.8
        },
        {
            "episode": 3,
            "rating": 8.5
        },
        {
            "episode": 4,
            "rating": 9.5
        },
        {
            "episode": 5,
            "rating": 8.2
        },
        {
            "episode": 6,
            "rating": 9.3
        },
        {
            "episode": 7,
            "rating": 8.4
        },
        {
            "episode": 8,
            "rating": 7.6
        },
        {
            "episode": 9,
            "rating": 8.5
        },
        {
            "episode": 10,
            "rating": 9.3
        }
    ],
    [
        {
            "episode": 1,
            "rating": 9.6
        },
        {
            "episode": 2,
            "rating": 8.1
        },
        {
            "episode": 3,
            "rating": 9.3
        },
        {
            "episode": 4,
            "rating": 8.1
        },
        {
            "episode": 5,
            "rating": 8.4
        },
        {
            "episode": 6,
            "rating": 8.8
        },
        {
            "episode": 7,
            "rating": 9.8
        },
        {
            "episode": 8,
            "rating": 8.9
        },
        {
            "episode": 9,
            "rating": 7.9
        },
        {
            "episode": 10,
            "rating": 8.2
        }
    ],
    [
        {
            "episode": 1,
            "rating": 8.9
        },
        {
            "episode": 2,
            "rating": 8.2
        },
        {
            "episode": 3,
            "rating": 8.3
        },
        {
            "episode": 4,
            "rating": 7.3
        },
        {
            "episode": 5,
            "rating": 8.8
        },
        {
            "episode": 6,
            "rating": 8.0
        },
        {
            "episode": 7,
            "rating": 8.0
        },
        {
            "episode": 8,
            "rating": 9.4
        },
        {
            "episode": 9,
            "rating": 7.7
        },
        {
            "episode": 10,
            "rating": 9.1
        }
    ],
    [
        {
            "episode": 1,
            "rating": 9.0
        },
        {
            "episode": 2,
            "rating": 8.7
        },
        {
            "episode": 3,
            "rating": 7.8
        },
        {
            "episode": 4,
            "rating": 5.7
        },
        {
            "episode": 5,
            "rating": 7.0
        },
        {
            "episode": 6,
            "rating": 7.1
        },
        {
            "episode": 7,
            "rating": 6.4
        },
        {
            "episode": 8,
            "rating": 8.2
        },
        {
            "episode": 9,
            "rating": 8.3
        },
        {
            "episode": 10,
            "rating": 9.3
        }
    ],
    [
        {
            "episode": 1,
            "rating": 8.6
        },
        {
            "episode": 2,
            "rating": 7.9
        },
        {
            "episode": 3,
            "rating": 7.8
        },
        {
            "episode": 4,
            "rating": 8.5
        },
        {
            "episode": 5,
            "rating": 8.2
        },
        {
            "episode": 6,
            "rating": 8.0
        },
        {
            "episode": 7,
            "rating": 8.0
        },
        {
            "episode": 8,
            "rating": 8.4
        },
        {
            "episode": 9,
            "rating": 7.5
        },
        {
            "episode": 10,
            "rating": 8.1
        }
    ]
]