[
    [
        {
            "episode": 1,
            "rating": 7.699999809265137,
            "id": "tt3532582"
        },
        {
            "episode": 2,
            "rating": 7.5,
            "id": "tt3532584"
        },
        {
            "episode": 3,
            "rating": 7.5,
            "id": "tt3532594"
        },
        {
            "episode": 4,
            "rating": 7.599999904632568,
            "id": "tt3532588"
        },
        {
            "episode": 5,
            "rating": 7.900000095367432,
            "id": "tt3532592"
        },
        {
            "episode": 6,
            "rating": 7.900000095367432,
            "id": "tt3532598"
        },
        {
            "episode": 7,
            "rating": 7.699999809265137,
            "id": "tt3532596"
        },
        {
            "episode": 8,
            "rating": 7.699999809265137,
            "id": "tt3532604"
        },
        {
            "episode": 9,
            "rating": 7.800000190734863,
            "id": "tt3532602"
        },
        {
            "episode": 10,
            "rating": 8.300000190734863,
            "id": "tt3532600"
        }
    ],
    [
        {
            "episode": 1,
            "rating": 7.900000095367432,
            "id": "tt4836146"
        },
        {
            "episode": 2,
            "rating": 7.599999904632568,
            "id": "tt4836142"
        },
        {
            "episode": 3,
            "rating": 7.5,
            "id": "tt4836148"
        },
        {
            "episode": 4,
            "rating": 7.400000095367432,
            "id": "tt4836152"
        },
        {
            "episode": 5,
            "rating": 7.699999809265137,
            "id": "tt4836144"
        },
        {
            "episode": 6,
            "rating": 7.900000095367432,
            "id": "tt4836154"
        },
        {
            "episode": 7,
            "rating": 8.100000381469727,
            "id": "tt4836164"
        },
        {
            "episode": 8,
            "rating": 7.800000190734863,
            "id": "tt4836158"
        },
        {
            "episode": 9,
            "rating": 8.100000381469727,
            "id": "tt4836168"
        },
        {
            "episode": 10,
            "rating": 8.399999618530273,
            "id": "tt4836160"
        }
    ],
    [
        {
            "episode": 1,
            "rating": 7.800000190734863,
            "id": "tt5776090"
        },
        {
            "episode": 2,
            "rating": 7.599999904632568,
            "id": "tt5776092"
        },
        {
            "episode": 3,
            "rating": 7.400000095367432,
            "id": "tt5776100"
        },
        {
            "episode": 4,
            "rating": 7.599999904632568,
            "id": "tt5776096"
        },
        {
            "episode": 5,
            "rating": 7.900000095367432,
            "id": "tt5776098"
        },
        {
            "episode": 6,
            "rating": 7.5,
            "id": "tt5776106"
        },
        {
            "episode": 7,
            "rating": 7.400000095367432,
            "id": "tt5776110"
        },
        {
            "episode": 8,
            "rating": 7.5,
            "id": "tt5776112"
        },
        {
            "episode": 9,
            "rating": 7.599999904632568,
            "id": "tt5776104"
        },
        {
            "episode": 10,
            "rating": 7.800000190734863,
            "id": "tt5776108"
        }
    ],
    [
        {
            "episode": 1,
            "rating": 7.400000095367432,
            "id": "tt7197046"
        },
        {
            "episode": 2,
            "rating": 7.5,
            "id": "tt7529244"
        },
        {
            "episode": 3,
            "rating": 7.199999809265137,
            "id": "tt7644786"
        },
        {
            "episode": 4,
            "rating": 7.199999809265137,
            "id": "tt7748144"
        },
        {
            "episode": 5,
            "rating": 7.900000095367432,
            "id": "tt7830868"
        },
        {
            "episode": 6,
            "rating": 7.5,
            "id": "tt7802292"
        },
        {
            "episode": 7,
            "rating": 7.699999809265137,
            "id": "tt7903648"
        },
        {
            "episode": 8,
            "rating": 7.300000190734863,
            "id": "tt7308524"
        }
    ]
]