[
    [
        {
            "episode": 1,
            "rating": 6.8,
            "id": "tt7020610"
        },
        {
            "episode": 2,
            "rating": 7.2,
            "id": "tt7269728"
        },
        {
            "episode": 3,
            "rating": 6.9,
            "id": "tt7269754"
        },
        {
            "episode": 4,
            "rating": 7.3,
            "id": "tt7269764"
        },
        {
            "episode": 5,
            "rating": 7.2,
            "id": "tt7269774"
        },
        {
            "episode": 6,
            "rating": 7.2,
            "id": "tt7269784"
        },
        {
            "episode": 7,
            "rating": 7.2,
            "id": "tt7269788"
        },
        {
            "episode": 8,
            "rating": 7.4,
            "id": "tt7269796"
        },
        {
            "episode": 9,
            "rating": 7.1,
            "id": "tt7269802"
        },
        {
            "episode": 10,
            "rating": 7.5,
            "id": "tt7269816"
        },
        {
            "episode": 11,
            "rating": 7.2,
            "id": "tt7269814"
        },
        {
            "episode": 12,
            "rating": 7.3,
            "id": "tt7269820"
        }
    ],
    [
        {
            "episode": 1,
            "rating": 7.6,
            "id": "tt8988918"
        },
        {
            "episode": 2,
            "rating": 7.5,
            "id": "tt8988920"
        },
        {
            "episode": 3,
            "rating": 7.4,
            "id": "tt8988922"
        },
        {
            "episode": 4,
            "rating": 7.6,
            "id": "tt8988924"
        },
        {
            "episode": 5,
            "rating": 7.5,
            "id": "tt8988926"
        },
        {
            "episode": 6,
            "rating": 7.4,
            "id": "tt8988928"
        },
        {
            "episode": 7,
            "rating": 7.7,
            "id": "tt8988930"
        },
        {
            "episode": 8,
            "rating": 7.4,
            "id": "tt8988932"
        },
        {
            "episode": 9,
            "rating": 7.8,
            "id": "tt8988934"
        },
        {
            "episode": 10,
            "rating": 8.5,
            "id": "tt8988938"
        }
    ]
]