[
    [
        {
            "episode": 1,
            "rating": 8.199999809265137,
            "id": "tt9381924"
        },
        {
            "episode": 2,
            "rating": 7.300000190734863,
            "id": "tt9420276"
        },
        {
            "episode": 3,
            "rating": 7.400000095367432,
            "id": "tt9420278"
        },
        {
            "episode": 4,
            "rating": 7.199999809265137,
            "id": "tt9420280"
        },
        {
            "episode": 5,
            "rating": 6.900000095367432,
            "id": "tt9420282"
        },
        {
            "episode": 6,
            "rating": 7.800000190734863,
            "id": "tt9420284"
        },
        {
            "episode": 7,
            "rating": 8.300000190734863,
            "id": "tt9420288"
        },
        {
            "episode": 8,
            "rating": 7.800000190734863,
            "id": "tt9420290"
        },
        {
            "episode": 9,
            "rating": 7.300000190734863,
            "id": "tt10073428"
        },
        {
            "episode": 10,
            "rating": 7.599999904632568,
            "id": "tt10073432"
        }
    ],
    [
        {
            "episode": 1,
            "rating": 8.0,
            "id": "tt11596676"
        },
        {
            "episode": 2,
            "rating": 7.900000095367432,
            "id": "tt14435038"
        },
        {
            "episode": 3,
            "rating": 7.099999904632568,
            "id": "tt14435136"
        },
        {
            "episode": 4,
            "rating": 6.400000095367432,
            "id": "tt14435140"
        },
        {
            "episode": 5,
            "rating": 6.599999904632568,
            "id": "tt14435150"
        },
        {
            "episode": 6,
            "rating": 6.199999809265137,
            "id": "tt14435154"
        },
        {
            "episode": 7,
            "rating": 5.400000095367432,
            "id": "tt14435170"
        },
        {
            "episode": 8,
            "rating": 6.199999809265137,
            "id": "tt14440086"
        },
        {
            "episode": 9,
            "rating": 5.699999809265137,
            "id": "tt14435168"
        },
        {
            "episode": 10,
            "rating": 6.800000190734863,
            "id": "tt14435178"
        }
    ],
    [
        {
            "episode": 1,
            "rating": 8.399999618530273,
            "id": "tt15393200"
        },
        {
            "episode": 2,
            "rating": 8.199999809265137,
            "id": "tt22012632"
        },
        {
            "episode": 3,
            "rating": 8.399999618530273,
            "id": "tt19402762"
        },
        {
            "episode": 4,
            "rating": 9.0,
            "id": "tt22012530"
        },
        {
            "episode": 5,
            "rating": 8.899999618530273,
            "id": "tt22012754"
        },
        {
            "episode": 6,
            "rating": 8.899999618530273,
            "id": "tt22012534"
        },
        {
            "episode": 7,
            "rating": 8.199999809265137,
            "id": "tt22012536"
        },
        {
            "episode": 8,
            "rating": 8.600000381469727,
            "id": "tt22012816"
        },
        {
            "episode": 9,
            "rating": 9.300000190734863,
            "id": "tt22012822"
        },
        {
            "episode": 10,
            "rating": 9.399999618530273,
            "id": "tt22012830"
        }
    ]
]